neural_learn/__init__.py
neural_learn/main.py
neural_learn-0.0.1.dist-info/LICENSE
neural_learn-0.0.1.dist-info/METADATA
neural_learn-0.0.1.dist-info/WHEEL
neural_learn-0.0.1.dist-info/top_level.txt
neural_learn-0.0.1.dist-info/RECORD
